syphus/__init__.py
syphus/cli/__init__.py
syphus/cli/converter.py
syphus/cli/data_generator.py
syphus/cli/initializer.py
syphus/cli/output_merger.py
syphus/cli/syphus_cli.py
syphus/data_generator/__init__.py
syphus/data_generator/gpt_manager.py
syphus/data_generator/gpt_params_settings.py
syphus/data_generator/openai_settings.py
syphus/data_generator/response.py
syphus/data_generator/syphus.py
syphus/dataset/__init__.py
syphus/dataset/dataset.py
syphus/dataset/m3it.py
syphus/dataset/mmbench.py
syphus/prompts/__init__.py
syphus/prompts/in_context_example.py
syphus/prompts/info.py
syphus/prompts/prompts.py
syphus/prompts/qa_pair.py
syphus/resources/template/config/gpt_info.yaml
syphus/resources/template/config/prompts.yaml
syphus/resources/template/resources/media_infos.json
syphus/utils/__init__.py
syphus/utils/file_format.py
syphus/utils/image_processor.py
syphus/utils/jsonl.py
syphus/utils/settings.py
syphus/utils/yaml.py
syphus-0.0.6.4.dist-info/LICENSE
syphus-0.0.6.4.dist-info/METADATA
syphus-0.0.6.4.dist-info/WHEEL
syphus-0.0.6.4.dist-info/entry_points.txt
syphus-0.0.6.4.dist-info/top_level.txt
syphus-0.0.6.4.dist-info/RECORD
