Metadata-Version: 2.1
Name: syphus
Version: 0.0.6.4
Summary: Syphus: Automatic Instruction-Response Generation Pipeline
Home-page: https://github.com/pufanyi/syphus
Author: Fanyi Pu
Author-email: FPU001@e.ntu.edu.sg
Classifier: Development Status :: 3 - Alpha
Classifier: Intended Audience :: Developers
Classifier: Programming Language :: Python :: 3
Classifier: Programming Language :: Python :: 3.9
Classifier: Programming Language :: Python :: 3.10
Classifier: Programming Language :: Python :: 3.11
License-File: LICENSE
Requires-Dist: ruamel.yaml >=0.17.32
Requires-Dist: PyYAML >=6.0.1
Requires-Dist: openai >=0.27.8
Requires-Dist: orjson >=3.9.4
Requires-Dist: opencv-python >=4.8.0.76
Requires-Dist: Pillow >=10.0.1
Requires-Dist: pandas >=2.1.0
Requires-Dist: requests >=2.31.0
